autoscout24/__init__.py
autoscout24/client.py
autoscout24/config.py
autoscout24-0.0.3.dist-info/METADATA
autoscout24-0.0.3.dist-info/WHEEL
autoscout24-0.0.3.dist-info/RECORD
