Metadata-Version: 2.3
Name: autoscout24
Version: 0.0.3
Summary: Official Python client parser for the Carapis AutoScout24 API. Access real-time vehicle data via a powerful REST API. (AutoScout24)
License: MIT
Keywords: autoscout24,autoscout24_api,carapis,car_data,vehicle_data,used_car_api,client,parser,automotive,AutoScout24
Author: Carapis.com
Author-email: info@carapis.com
Requires-Python: >=3.9,<4.0
Classifier: Development Status :: 4 - Beta
Classifier: Intended Audience :: Developers
Classifier: License :: OSI Approved :: MIT License
Classifier: Operating System :: OS Independent
Classifier: Programming Language :: Python :: 3
Classifier: Programming Language :: Python :: 3.9
Classifier: Programming Language :: Python :: 3.10
Classifier: Programming Language :: Python :: 3.11
Classifier: Programming Language :: Python :: 3.12
Classifier: Programming Language :: Python :: 3.13
Classifier: Topic :: Internet :: WWW/HTTP
Classifier: Topic :: Software Development :: Libraries :: Python Modules
Requires-Dist: python-dotenv (>=1.0.0,<2.0.0)
Requires-Dist: pyyaml (>=6.0.1,<7.0.0)
Requires-Dist: requests (>=2.31.0,<3.0.0)
Project-URL: Documentation, https://carapis.com/docs
Project-URL: Homepage, https://carapis.com/
Project-URL: Repository, https://github.com/markolofsen/carapis-autoscout24
